simple_mcp/__init__.py
simple_mcp/server.py
simple_mcp_example-0.1.1.dist-info/licenses/LICENSE
simple_mcp_example-0.1.1.dist-info/METADATA
simple_mcp_example-0.1.1.dist-info/WHEEL
simple_mcp_example-0.1.1.dist-info/top_level.txt
simple_mcp_example-0.1.1.dist-info/RECORD
