Metadata-Version: 2.4
Name: simple-mcp-example
Version: 0.1.1
Summary: A simple MCP server example
Author-email: Your Name <your.email@example.com>
Classifier: Programming Language :: Python :: 3
Classifier: License :: OSI Approved :: MIT License
Classifier: Operating System :: OS Independent
Requires-Python: >=3.8
License-File: LICENSE
Requires-Dist: fastmcp>=0.1.0
Dynamic: license-file
